pycombat/__init__.py
pycombat/pycombat.py
pycombat-0.20.dist-info/METADATA
pycombat-0.20.dist-info/WHEEL
pycombat-0.20.dist-info/top_level.txt
pycombat-0.20.dist-info/RECORD
