Metadata-Version: 2.1
Name: pycombat
Version: 0.20
Summary: Python version of data harmonisation technique Combat
Home-page: https://github.com/CoAxLab/pycombat
Author: CoAxLab
Author-email: jrasero.daparte@gmail.com
License: UNKNOWN
Project-URL: Bug Tracker, https://github.com/CoAxLab/pycombat/issues
Platform: UNKNOWN
Classifier: Programming Language :: Python :: 3
Classifier: License :: OSI Approved :: MIT License
Classifier: Operating System :: OS Independent
Requires-Python: >=3.6
Requires-Dist: numpy
Requires-Dist: scikit-learn
